{"version":2,"baseVals":{"rating":5,"gammaadj":1.9,"echo_zoom":1.169,"wave_brighten":0,"wave_a":4.1,"wave_scale":0.443,"wave_smoothing":0.63,"wave_mystery":-0.4,"modwavealphastart":0.71,"modwavealphaend":1.3,"zoom":1.135,"warp":0.01605,"wave_r":0.65,"wave_g":0.65,"wave_b":0.65,"ob_size":0,"ob_a":1,"mv_x":64,"mv_y":48,"mv_l":0.5,"mv_r":0.35,"mv_g":0.35,"mv_b":0.35,"mv_a":0},"shapes":[{"baseVals":{"enabled":0},"init_eqs_str":"","frame_eqs_str":"","init_eqs_eel":"","frame_eqs_eel":""},{"baseVals":{"enabled":0},"init_eqs_str":"","frame_eqs_str":"","init_eqs_eel":"","frame_eqs_eel":""},{"baseVals":{"enabled":0},"init_eqs_str":"","frame_eqs_str":"","init_eqs_eel":"","frame_eqs_eel":""},{"baseVals":{"enabled":0},"init_eqs_str":"","frame_eqs_str":"","init_eqs_eel":"","frame_eqs_eel":""}],"waves":[{"baseVals":{"enabled":1,"samples":42,"usedots":1,"thick":1,"additive":1,"scaling":81.95444,"smoothing":1,"g":0.4,"b":0},"init_eqs_str":"a.wave_x=0;a.q2=0;a.q3=0;a.q1=0;","frame_eqs_str":"a.wave_x=1;a.r=a.q2;a.g=a.q3;a.b=a.q1;","point_eqs_str":"a.x=.001*Math.floor(rand(1E3));a.y=.001*Math.floor(rand(1E3));","init_eqs_eel":"","frame_eqs_eel":"wave_x=1;\nr = q2;\ng = q3;\nb = q1;","point_eqs_eel":"x=int(rand(1000))*0.001;\ny=int(rand(1000))*0.001;\n//r=0.9;\n//g=1;\n//b=1"},{"baseVals":{"enabled":0},"init_eqs_str":"","frame_eqs_str":"","point_eqs_str":"","init_eqs_eel":"","frame_eqs_eel":"","point_eqs_eel":""},{"baseVals":{"enabled":0},"init_eqs_str":"","frame_eqs_str":"","point_eqs_str":"","init_eqs_eel":"","frame_eqs_eel":"","point_eqs_eel":""},{"baseVals":{"enabled":0},"init_eqs_str":"","frame_eqs_str":"","point_eqs_str":"","init_eqs_eel":"","frame_eqs_eel":"","point_eqs_eel":""}],"init_eqs_str":"a.q1=0;a.q2=0;a.q3=0;","frame_eqs_str":"a.zoom=.935*a.zoom+.04*(.6*Math.sin(.339*a.bass_att)+.1*Math.sin(.276*a.bass_att));a.rot+=.04*(.6*Math.sin(.381*a.time)+.4*Math.sin(.579*a.time));a.cx+=.003*(.6*Math.sin(.471*a.treb_att)+.4*Math.sin(.297*a.treb_att));a.cy+=.003*(.6*Math.sin(.379*a.mid_att)+.4*Math.sin(.351*a.mid_att));a.dx+=.003*(.6*Math.sin(.234*a.time)+.4*Math.sin(.277*a.time));a.rot+=.02*(Math.sin(2.134*a.time)+Math.sin(1.7134*a.time)+Math.sin(2.834*a.time));a.dx+=.01*(Math.sin(1.134*a.time)+Math.sin(.7134*\na.time)+Math.sin(2.334*a.time));a.dy+=.01*(Math.sin(1.8834*a.time)+Math.sin(1.0144*a.time)+Math.sin(1.334*a.time));a.q1+=.65*(.6*Math.sin(1.437*a.time)+.4*Math.sin(.97*a.time));a.q2+=.65*(.6*Math.sin(1.344*a.time)+.4*Math.sin(.841*a.time));a.q3+=.65*(.6*Math.sin(1.251*a.time)+.4*Math.sin(1.055*a.time));a.wave_r=a.q1;a.wave_g=a.q2;a.wave_b=a.q3;","pixel_eqs_str":"","init_eqs_eel":"","frame_eqs_eel":"//wave_g = wave_g + 0.100*( 0.90*sin(0.583*time) + 0.10*sin(1.006*time) );\n//wave_b = wave_b + 0.100*( 0.90*sin(0.993*time) + 0.10*sin(0.933*time) );\nzoom = 0.935*zoom + 0.04*( 0.60*sin(0.339*bass_att) + 0.10*sin(0.276*bass_att) );\nrot = rot + 0.040*( 0.60*sin(0.381*time) + 0.40*sin(0.579*time) );\ncx = cx + 0.003*( 0.60*sin(0.471*treb_att) + 0.40*sin(0.297*treb_att) );\ncy = cy + 0.003*( 0.60*sin(0.379*mid_att) + 0.40*sin(0.351*mid_att) );\ndx = dx + 0.003*( 0.60*sin(0.234*time) + 0.40*sin(0.277*time) );\nrot=rot+0.02*(sin(time*2.134)+sin(time*1.7134)+sin(time*2.834));\ndx=dx+0.01*(sin(time*1.134)+sin(time*0.7134)+sin(time*2.334));\ndy=dy+0.01*(sin(time*1.8834)+sin(time*1.0144)+sin(time*1.334));\n\nq1 = q1 + 0.650*( 0.60*sin(1.437*time) + 0.40*sin(0.970*time) );\nq2 = q2 + 0.650*( 0.60*sin(1.344*time) + 0.40*sin(0.841*time) );\nq3 = q3 + 0.650*( 0.60*sin(1.251*time) + 0.40*sin(1.055*time) );\nwave_r = q1;\nwave_g = q2;\nwave_b = q3;","pixel_eqs_eel":"","warp":" shader_body { \n  vec3 ret_1;\n  ret_1 = texture (sampler_main, uv).xyz;\n  ret_1 = (ret_1 + ((\n    (ret_1 - mix (((texture (sampler_blur2, uv).xyz * scale2) + bias2), ((texture (sampler_blur1, uv).xyz * scale1) + bias1), uv_orig.xxx))\n   * 0.3) - 0.04));\n  ret_1 = (ret_1 * 0.95);\n  ret_1 = (ret_1 + 0.04);\n  ret_1 = mix (ret_1, vec3(dot (ret_1, vec3(0.32, 0.49, 0.29))), vec3(0.2, 0.2, 0.2));\n  vec4 tmpvar_2;\n  tmpvar_2.w = 1.0;\n  tmpvar_2.xyz = ret_1;\n  ret = tmpvar_2.xyz;\n }","comp":" shader_body { \n  vec2 uv_1;\n  vec3 ret_2;\n  uv_1 = (uv * 2.0);\n  uv_1 = (1.0 - abs((\n    (fract((uv_1 * 0.5)) * 2.0)\n   - 1.0)));\n  vec2 tmpvar_3;\n  tmpvar_3 = (texsize.zw * 6.0);\n  vec3 tmpvar_4;\n  tmpvar_4 = (((texture (sampler_blur1, \n    (uv_1 + (vec2(1.0, 0.0) * tmpvar_3))\n  ).xyz * scale1) + bias1) - ((texture (sampler_blur1, \n    (uv_1 - (vec2(1.0, 0.0) * tmpvar_3))\n  ).xyz * scale1) + bias1));\n  vec3 tmpvar_5;\n  tmpvar_5 = (((texture (sampler_blur1, \n    (uv_1 + (vec2(0.0, 1.0) * tmpvar_3))\n  ).xyz * scale1) + bias1) - ((texture (sampler_blur1, \n    (uv_1 - (vec2(0.0, 1.0) * tmpvar_3))\n  ).xyz * scale1) + bias1));\n  vec2 tmpvar_6;\n  tmpvar_6.x = dot (tmpvar_4, vec3(0.32, 0.49, 0.29));\n  tmpvar_6.y = dot (tmpvar_5, vec3(0.32, 0.49, 0.29));\n  vec2 tmpvar_7;\n  tmpvar_7 = (uv_1 - (0.25 * tmpvar_6));\n  vec2 tmpvar_8;\n  tmpvar_8.x = dot (tmpvar_4, vec3(0.32, 0.49, 0.29));\n  tmpvar_8.y = dot (tmpvar_5, vec3(0.32, 0.49, 0.29));\n  vec2 tmpvar_9;\n  tmpvar_9 = (uv_1 + (0.25 * tmpvar_8));\n  ret_2 = ((0.8 * (\n    (texture (sampler_blur3, tmpvar_7).xyz * scale3)\n   + bias3)) - ((texture (sampler_blur1, tmpvar_7).xyz * scale1) + bias1));\n  ret_2 = (ret_2 + (0.6 * (\n    (texture (sampler_blur1, uv_1).xyz * scale1)\n   + bias1)));\n  ret_2 = (ret_2 - ((\n    (texture (sampler_blur2, tmpvar_9).xyz * scale2)\n   + bias2) - (\n    (texture (sampler_blur1, tmpvar_9).xyz * scale1)\n   + bias1)));\n  ret_2 = (ret_2 + ((1.2 * texture (sampler_main, tmpvar_9).xyz) + (0.15 * \n    ((texture (sampler_blur1, tmpvar_9).xyz * scale1) + bias1)\n  )));\n  ret_2 = (ret_2 + 1.0);\n  float tmpvar_10;\n  tmpvar_10 = dot (ret_2, vec3(0.32, 0.49, 0.29));\n  ret_2 = (mix (vec3(tmpvar_10), (\n    (0.75 * vec3(tmpvar_10))\n   * \n    dot ((((0.6 * \n      ((texture (sampler_blur3, tmpvar_7).xyz * scale3) + bias3)\n    ) - (0.7 * texture (sampler_main, uv_1).xyz)) - (0.3 * (\n      (texture (sampler_blur1, tmpvar_9).xyz * scale1)\n     + bias1))), vec3(0.32, 0.49, 0.29))\n  ), pow (hue_shader, vec3(tmpvar_10))) * 0.8);\n  ret_2 = (ret_2 * ret_2);\n  vec3 tmpvar_11;\n  tmpvar_11 = sqrt(ret_2);\n  ret_2 = tmpvar_11;\n  vec4 tmpvar_12;\n  tmpvar_12.w = 1.0;\n  tmpvar_12.xyz = tmpvar_11;\n  ret = tmpvar_12.xyz;\n }","warp_hlsl":"shader_body\n{\n    // sample previous frame\n    ret.xyz = tex2D( sampler_main, uv ).xyz;\n\n      // take the difference between the crisp and blurred images,\n      // then add it back into the image.  Creates spots and stripes over time.\n      float3 b = lerp(GetBlur2(uv),GetBlur1(uv),uv_orig.x);//GetBlur2(uv);\n      ret.xyz += (ret.xyz - b)*0.3 - 0.04;\n      ret.xyz *= 0.95;\n\n      // add noise:\n      float2 dither_uv = uv_orig*texsize.xy*texsize_noise_lq.zw * 0.4 + rand_frame.xy;\n      ret.xyz += 0.04;//(tex2D(sampler_noise_lq, dither_uv).xyz-0.5)*0.3;\n\n      // desaturate over time, to keep the globs white\n      ret.xyz = lerp(ret.xyz, lum(ret.xyz), 0.2);\n}","comp_hlsl":"shader_body\n{\n\nuv *= 2;\nuv = 1.0 - abs( frac( uv * 0.5 ) * 2.0 - 1.0 ); // Eo.S' mirror code\n\n\n//Code bits by Flexi and Geiss\n\n    float2 d = texsize.zw*6;\n    float3 dx = ( GetBlur1(uv+float2(1,0)*d)-GetBlur1(uv-float2(1,0)*d) );\n    float3 dy = ( GetBlur1(uv+float2(0,1)*d)-GetBlur1(uv-float2(0,1)*d) );\nfloat2 uv_y = uv-.25*(float2(lum(dx),lum(dy)));\nfloat2 uv_y2 = uv+.25*(float2(lum(dx),lum(dy)));\n\n\nret = .8*GetBlur3(uv_y)-GetBlur1(uv_y);\nret += .6*GetBlur1(uv);\nret -= (GetBlur2(uv_y2)-GetBlur1(uv_y2));\nret += 1.2*GetPixel(uv_y2)+.15*GetBlur1(uv_y2);\nret += 1;\nret = lum(ret);\nret = lerp(ret,.75*ret*lum(.6*GetBlur3(uv_y)-.7*GetPixel(uv)-.3*GetBlur1(uv_y2)),pow(hue_shader,ret));\nret *= .8;\nret *= ret;\nret = sqrt(ret);\n\n}"}