{"version":2,"baseVals":{"rating":5,"gammaadj":0.16,"decay":0.96,"echo_zoom":0.997,"echo_alpha":0.5,"echo_orient":1,"wave_thick":1,"wave_brighten":0,"darken":1,"wave_a":0.004,"wave_scale":0.242,"wave_smoothing":0,"wave_mystery":-0.44,"modwavealphastart":1,"modwavealphaend":1,"zoom":1.055,"warp":0.02349,"wave_y":0.04,"mv_x":64,"mv_y":48,"mv_l":0,"mv_b":0,"mv_a":0,"b1ed":0.3},"shapes":[{"baseVals":{"enabled":1,"sides":100,"thickoutline":1,"y":0.04,"rad":0.01,"tex_ang":0.12566,"tex_zoom":1.51878,"r":0,"a":0,"g2":0,"b2":0.01,"border_a":0},"init_eqs_str":"","frame_eqs_str":"","init_eqs_eel":"","frame_eqs_eel":""},{"baseVals":{"sides":100,"additive":1,"thickoutline":1,"textured":1,"x":0.49,"rad":1.32907,"tex_zoom":0.49831,"g":1,"b":1,"a":0.99,"g2":0,"border_a":0,"enabled":0},"init_eqs_str":"","frame_eqs_str":"","init_eqs_eel":"","frame_eqs_eel":""},{"baseVals":{"thickoutline":1,"x":1,"rad":3.0054,"tex_ang":0.12566,"tex_zoom":1.51878,"r":0,"g":1,"g2":0,"a2":1,"border_a":0,"enabled":0},"init_eqs_str":"","frame_eqs_str":"","init_eqs_eel":"","frame_eqs_eel":""},{"baseVals":{"thickoutline":1,"x":1,"rad":0.39872,"tex_ang":0.12566,"tex_zoom":1.51878,"g":1,"b":1,"r2":1,"b2":1,"a2":1,"border_a":0,"enabled":0},"init_eqs_str":"","frame_eqs_str":"","init_eqs_eel":"","frame_eqs_eel":""}],"waves":[{"baseVals":{"enabled":1,"thick":1,"additive":1,"scaling":2.0231,"smoothing":0,"r":0,"b":0},"init_eqs_str":"a.tt3=0;a.tt2=0;a.tt1=0;a.d=0;a.t2=0;a.t3=0;a.t4=0;a.cl=0;","frame_eqs_str":"a.r=1;a.g=0;a.b=1;","point_eqs_str":"a.tt3=.6*a.tt3+1*a.value1;a.tt2=.7*a.tt2+.2*a.tt3;a.tt1=.8*a.tt1+.1*a.tt2;a.d=.9*a.d+.2*a.tt1;a.y=.6+a.d*a.sample*(1-a.sample)*2;a.x=-.05+1.1*a.sample;","init_eqs_eel":"t2 = 0;\nt3 = 0;\nt4 = 0;\ncl = 0;","frame_eqs_eel":"r = 1; g = 0; b = 1;","point_eqs_eel":"tt3 = tt3*0.6 + (value1)*1;\ntt2 = tt2*0.7 + tt3*0.2;\ntt1 = tt1*0.8 + tt2*0.1;\nd = d*0.9 + tt1*0.2;\n\ny = 0.6 + d*sample*(1-sample)*2;\nx =  -0.05 + sample*1.1;"},{"baseVals":{"scaling":2.44415,"smoothing":0,"enabled":0},"init_eqs_str":"t2 = 0;\nt3 = 0;\nt4 = 0;\ncl = 0;","frame_eqs_str":"t8 = 1;","point_eqs_str":"t8 = -t8;\ny = sample;\nx = 0.5 + t8*0.005;\n\npi3 = 3.1415*2*0.3333;\nt = time + sample*2;\nc=2;\n\nr = sin(t)*c;\ng = sin(t+pi3)*c;\n\nb = sin(t-pi3)*c;\n\n\nr = if(above(r,1),1,r);\nr = if(below(r,0),0,r);\ng = if(above(g,1),1,g);\ng = if(below(g,0),0,g);\nb = if(above(b,1),1,b);\nb = if(below(b,0),0,b);\n","init_eqs_eel":"t2 = 0;\nt3 = 0;\nt4 = 0;\ncl = 0;","frame_eqs_eel":"t8 = 1;","point_eqs_eel":"t8 = -t8;\ny = sample;\nx = 0.5 + t8*0.005;\n\npi3 = 3.1415*2*0.3333;\nt = time + sample*2;\nc=2;\n\nr = sin(t)*c;\ng = sin(t+pi3)*c;\n\nb = sin(t-pi3)*c;\n\n\nr = if(above(r,1),1,r);\nr = if(below(r,0),0,r);\ng = if(above(g,1),1,g);\ng = if(below(g,0),0,g);\nb = if(above(b,1),1,b);\nb = if(below(b,0),0,b);\n"},{"baseVals":{"thick":1,"additive":1,"scaling":100,"smoothing":0.6,"r":0,"g":0.4,"a":0.3,"enabled":0},"init_eqs_str":"","frame_eqs_str":"t1 = q1;\nt2 = q2;\nt3 = q3;\nt4 = q4;\nt5 = q5;\nt6 = q6;\nt7 = q7;\nt8 = q8;","point_eqs_str":"sample = 1-sample;\nxxx = xx;\nyyy = yy;\nxx = pow(sample,5)*t1 + 5*pow(sample,4)*(1-sample)*t1 + 10*pow(sample,3)*sqr(1-sample)*t2\n+ 10*sqr(sample)*pow(1-sample,3)*t3 + 5*pow(1-sample,4)*sample*t4 + pow(1-sample,5)*t4;\n\nyy = pow(sample,5)*t5 + 5*pow(sample,4)*(1-sample)*t5 + 10*pow(sample,3)*sqr(1-sample)*t6\n+ 10*sqr(sample)*pow(1-sample,3)*t7 + 5*pow(1-sample,4)*sample*t8 + pow(1-sample,5)*t8;\nd = 1/sqrt(sqr(xx-xxx)+sqr(yy-yyy));\nx = xx + sample*(1-sample)*(value1-value2)*(yy-yyy)*d;\ny = yy - sample*(1-sample)*(value1-value2)*(xx-xxx)*d;","init_eqs_eel":"","frame_eqs_eel":"t1 = q1;\nt2 = q2;\nt3 = q3;\nt4 = q4;\nt5 = q5;\nt6 = q6;\nt7 = q7;\nt8 = q8;","point_eqs_eel":"sample = 1-sample;\nxxx = xx;\nyyy = yy;\nxx = pow(sample,5)*t1 + 5*pow(sample,4)*(1-sample)*t1 + 10*pow(sample,3)*sqr(1-sample)*t2\n+ 10*sqr(sample)*pow(1-sample,3)*t3 + 5*pow(1-sample,4)*sample*t4 + pow(1-sample,5)*t4;\n\nyy = pow(sample,5)*t5 + 5*pow(sample,4)*(1-sample)*t5 + 10*pow(sample,3)*sqr(1-sample)*t6\n+ 10*sqr(sample)*pow(1-sample,3)*t7 + 5*pow(1-sample,4)*sample*t8 + pow(1-sample,5)*t8;\nd = 1/sqrt(sqr(xx-xxx)+sqr(yy-yyy));\nx = xx + sample*(1-sample)*(value1-value2)*(yy-yyy)*d;\ny = yy - sample*(1-sample)*(value1-value2)*(xx-xxx)*d;"},{"baseVals":{"usedots":1,"scaling":2.44415,"smoothing":0,"r":0,"g":0,"enabled":0},"init_eqs_str":"t2 = 0;\nt3 = 0;\nt4 = 0;\ncl = 0;","frame_eqs_str":"t8 = 1;","point_eqs_str":"t8 = -t8;\ny = (1+t8)*0.01;\nx = sample;","init_eqs_eel":"t2 = 0;\nt3 = 0;\nt4 = 0;\ncl = 0;","frame_eqs_eel":"t8 = 1;","point_eqs_eel":"t8 = -t8;\ny = (1+t8)*0.01;\nx = sample;"}],"init_eqs_str":"","frame_eqs_str":"a.wave_r+=.2*(.9*Math.sin(2.753*a.time)+.4*Math.sin(2.315*a.time+1));a.wave_g+=.1*(.9*Math.sin(3.183*a.time+3)+.4*Math.sin(2.006*a.time+4));a.wave_b+=.1*(.9*Math.sin(2.393*a.time+5)+.4*Math.sin(2.733*a.time+2));a.zoom+=.013*(.6*Math.sin(.339*a.time)+.4*Math.sin(.276*a.time));a.rot+=.04*(.6*Math.sin(.381*a.time)+.4*Math.sin(.579*a.time));a.cx+=.003*(.6*Math.sin(.471*a.time)+.4*Math.sin(.297*a.time));a.cy+=.003*(.6*Math.sin(.379*a.time)+.4*Math.sin(.351*a.time));a.dx+=.003*(.6*\nMath.sin(.234*a.time)+.4*Math.sin(.277*a.time));a.rot+=.02*(Math.sin(2.134*a.time)+Math.sin(1.7134*a.time)+Math.sin(2.834*a.time));a.dx+=.0025*(Math.sin(1.134*a.time)+Math.sin(.7134*a.time)+Math.sin(2.334*a.time));a.dy+=.0025*(Math.sin(1.8834*a.time)+Math.sin(1.0144*a.time)+Math.sin(1.334*a.time));","pixel_eqs_str":"","init_eqs_eel":"","frame_eqs_eel":"wave_r = wave_r + 0.200*( 0.90*sin(2.753*time+0) + 0.40*sin(2.315*time+1) );\nwave_g = wave_g + 0.100*( 0.90*sin(3.183*time+3) + 0.40*sin(2.006*time+4) );\nwave_b = wave_b + 0.100*( 0.90*sin(2.393*time+5) + 0.40*sin(2.733*time+2) );\nzoom = zoom + 0.013*( 0.60*sin(0.339*time) + 0.40*sin(0.276*time) );\nrot = rot + 0.040*( 0.60*sin(0.381*time) + 0.40*sin(0.579*time) );\ncx = cx + 0.003*( 0.60*sin(0.471*time) + 0.40*sin(0.297*time) );\ncy = cy + 0.003*( 0.60*sin(0.379*time) + 0.40*sin(0.351*time) );\ndx = dx + 0.003*( 0.60*sin(0.234*time) + 0.40*sin(0.277*time) );\nrot=rot+0.02*(sin(time*2.134)+sin(time*1.7134)+sin(time*2.834));\ndx=dx+0.0025*(sin(time*1.134)+sin(time*0.7134)+sin(time*2.334));\ndy=dy+0.0025*(sin(time*1.8834)+sin(time*1.0144)+sin(time*1.334));","pixel_eqs_eel":"","warp":" shader_body { \n  vec3 ret_1;\n  ret_1 = texture (sampler_fc_main, uv).xyz;\n  vec2 tmpvar_2;\n  tmpvar_2 = (normalize((uv - uv_orig)) * texsize.zw);\n  vec4 tmpvar_3;\n  tmpvar_3.w = 0.0;\n  tmpvar_3.xyz = ret_1;\n  vec4 tmpvar_4;\n  tmpvar_4.w = 0.0;\n  tmpvar_4.xyz = max (tmpvar_3, (texture (sampler_main, (uv + tmpvar_2)) * 0.97)).xyz;\n  vec4 tmpvar_5;\n  tmpvar_5.w = 0.0;\n  tmpvar_5.xyz = max (tmpvar_4, (texture (sampler_main, (uv - tmpvar_2)) * 0.97)).xyz;\n  vec4 tmpvar_6;\n  tmpvar_6.w = 0.0;\n  tmpvar_6.xyz = max (tmpvar_5, (texture (sampler_main, (uv + \n    (tmpvar_2 * 2.0)\n  )) * 0.9)).xyz;\n  ret_1 = ((max (tmpvar_6, \n    (texture (sampler_main, (uv - (tmpvar_2 * 2.0))) * 0.9)\n  ).xyz - 0.004) * 0.98);\n  vec4 tmpvar_7;\n  tmpvar_7.w = 1.0;\n  tmpvar_7.xyz = ret_1;\n  ret = tmpvar_7.xyz;\n }","comp":" shader_body { \n  vec3 ret_1;\n  vec2 tmpvar_2;\n  tmpvar_2.x = (1.0 - uv.x);\n  tmpvar_2.y = uv.y;\n  vec3 tmpvar_3;\n  tmpvar_3 = vec3((texture (sampler_main, uv).x + texture (sampler_main, tmpvar_2).x));\n  vec2 tmpvar_4;\n  vec4 tmpvar_5;\n  tmpvar_5 = texture (sampler_blur1, uv);\n  tmpvar_4 = (((uv - 0.5) * (1.0 - \n    ((tmpvar_5.xyz * scale1) + bias1)\n  .zzz).xy) + 0.5);\n  vec3 tmpvar_6;\n  tmpvar_6 = (tmpvar_3 + clamp ((\n    pow (texture (sampler_main, tmpvar_4).zzz, vec3(0.5, 0.5, 0.5))\n   * \n    (1.0 - (tmpvar_3.x * 2.0))\n  ), 0.0, 1.0));\n  vec3 tmpvar_7;\n  tmpvar_7 = (tmpvar_6 + clamp ((\n    pow (((texture (sampler_blur1, tmpvar_4).xyz * scale1) + bias1).zzz, vec3(0.5, 0.5, 0.5))\n   * \n    (1.0 - (tmpvar_6.x * 2.0))\n  ), 0.0, 1.0));\n  vec2 tmpvar_8;\n  tmpvar_8.x = uv.x;\n  tmpvar_8.y = (1.0 - uv.y);\n  ret_1 = (pow (mix (\n    (vec3((((tmpvar_5.xyz * scale1) + bias1).x + ((texture (sampler_blur3, uv).xyz * scale3) + bias3).x)) + (((texture (sampler_blur1, tmpvar_2).xyz * scale1) + bias1).x + ((texture (sampler_blur3, tmpvar_2).xyz * scale3) + bias3).x))\n  , tmpvar_7, tmpvar_7), vec3(5.0, 1.0, 0.5)) + pow ((texture (sampler_main, tmpvar_8).yyy + texture (sampler_main, \n    (1.0 - uv)\n  ).yyy), vec3(0.6, 0.95, 5.0)));\n  vec4 tmpvar_9;\n  tmpvar_9 = texture (sampler_noisevol_hq, (((vec3(0.05, 0.05, 0.0) * tmpvar_4.xyy) * (\n    (q28 * texsize.xyy)\n   * texsize_noisevol_hq.zww)) + ((time * vec3(0.0, 0.0, 1.0)) * q31)));\n  if (((ret_1.x > (q26 * q13)) && (ret_1.x <= (q23 * q11)))) {\n    ret_1.z = (ret_1.z - (tmpvar_9.x * 0.5));\n  };\n  if (((ret_1.y > (q25 * q11)) && (ret_1.y <= (q22 * q12)))) {\n    ret_1.x = (ret_1.x - (tmpvar_9.y * 0.5));\n  };\n  if (((ret_1.z > (q24 * q12)) && (ret_1.z <= (q21 * q13)))) {\n    ret_1.y = (ret_1.y - (tmpvar_9.z * 0.5));\n  };\n  ret_1 = (ret_1 - ((slow_roam_sin.xyz * roam_cos.zxy) * 0.5));\n  vec4 tmpvar_10;\n  tmpvar_10.w = 1.0;\n  tmpvar_10.xyz = ret_1;\n  ret = tmpvar_10.xyz;\n }","warp_hlsl":"shader_body\n{\n    // sample previous frame\n    ret = tex2D( sampler_fc_main, uv ).xyz;\n    \n    // motion blur by Geiss\n    // 'v' points exactly one pixel, in the direction of motion\n    float2 v = normalize(uv-uv_orig)*texsize.zw;\n    float3 s;\n    ret = max(ret, tex2D(sampler_main, uv+v)*0.97);\n    ret = max(ret, tex2D(sampler_main, uv-v)*0.97);\n    ret = max(ret, tex2D(sampler_main, uv+v*2)*0.90);\n    ret = max(ret, tex2D(sampler_main, uv-v*2)*0.90);\n\n    // darken (decay) over time\n    ret = (ret-0.004)*0.98; //or try: ret -= 0.004;\n}","comp_hlsl":"shader_body\n{\n\n\n\nfloat2 uva = uv;\nfloat2 uvb = float2(1-uv.x,uv.y);\n\nret = tex2D(sampler_main, uva).x + tex2D(sampler_main, uvb).x;\n\nfloat3 blurs = GetBlur1(uva).x + GetBlur3(uva).x;\nblurs += GetBlur1(uvb).x + GetBlur3(uvb).x;\n\n\nfloat2 uv3 = (uv-.5)*(1-GetBlur1(uv).zzz)+.5;\nret += saturate(pow(tex2D(sampler_main, uv3).zzz,.5)*(1-ret.x*2)),\nret += saturate(pow(GetBlur1(uv3).zzz,.5)*(1-ret.x*2)),\n\n\nret = lerp (\nblurs,\nret,\npow(ret,1));\n\nret = pow(ret,float3(5,1,.5));\n\nret += pow(tex2D(sampler_main, float2(uv.x,1-uv.y)).yyy+tex2D(sampler_main, 1-uv).yyy,float3(.6,.95,5));\nfloat4 noise9 = tex3D(sampler_noisevol_hq, \n                      ((uv3.xyy*q28\n                       )*texsize.xyy*texsize_noisevol_hq.zww\n                      ).xyz*\n                      float3(1,1,0)*0.05 + \n                      time*float3(0,0,1)*q31\n                     );\nif(ret.x> q26*q13         && ret.x<= q23*q11        )ret.z -= (noise9).x*.5; \nif(ret.y> q25*q11         && ret.y<= q22*q12        )ret.x -= (noise9).y*.5; \nif(ret.z> q24*q12         && ret.z<= q21*q13        )ret.y -= (noise9).z*.5; \n\nret-=slow_roam_sin*roam_cos.zxy*.5;\n\n}"}