{"version":1,"baseVals":{"rating":5,"gammaadj":1.98,"decay":0.5,"echo_zoom":0.997,"echo_alpha":0.5,"echo_orient":3,"wave_thick":1,"wave_brighten":0,"wrap":0,"invert":1,"wave_a":0.004,"wave_scale":0.037,"wave_smoothing":0,"wave_mystery":-0.44,"modwavealphastart":1,"modwavealphaend":1,"warpanimspeed":0.803,"warpscale":1.22,"zoomexp":1.50374,"warp":0.31218,"wave_y":0.04,"ob_size":0.005,"ob_r":1,"ob_g":1,"ob_b":1,"ob_a":1,"ib_size":0,"ib_r":1,"ib_g":0,"ib_b":0.75,"ib_a":1,"mv_x":64,"mv_y":48,"mv_l":0,"mv_b":0,"mv_a":0,"b1ed":0},"shapes":[{"baseVals":{"enabled":1,"sides":60,"num_inst":200,"rad":2.96347,"tex_zoom":6.23873,"g":1,"b":1,"r2":1,"b2":1,"a2":1,"border_a":0},"init_eqs_str":"a.sa=0;","frame_eqs_str":"a.sa=div(a.instance,a.num_inst);a.x=.5+.2*Math.sin(.2*a.time);a.rad*=1-a.sa;a.r2=.5+.5*Math.sin(44*a.sa+.4*a.time);a.g2=a.r2;","init_eqs_eel":"","frame_eqs_eel":"sa=instance/num_inst;\n\nx=.5 + .2*sin(.2*time);\n\nrad=rad*(1-sa);\n\nr2=.5+.5*sin(44*sa+.4*time);\ng2=r2;\n"},{"baseVals":{"enabled":1,"sides":50,"num_inst":100,"x":0.74,"y":0.27,"rad":0.33668,"tex_zoom":0.81948,"g":1,"b":1,"g2":0,"b2":1,"a2":1,"border_a":0},"init_eqs_str":"a.sa=0;","frame_eqs_str":"a.sa=div(a.instance,a.num_inst);a.x=.5-.05*Math.sin(.57*a.time);a.y=.5+.05*Math.sin(.44*a.time);a.rad*=1-a.sa;a.r2=.5+.5*Math.sin(44*a.sa+.4*a.time);a.g2=a.r2;","init_eqs_eel":"","frame_eqs_eel":"sa=instance/num_inst;\n\nx=.5 - .05*sin(.57*time);\ny=.5 + .05*sin(.44*time);\n\nrad=rad*(1-sa);\n\nr2=.5+.5*sin(44*sa+.4*time);\ng2=r2;\n"},{"baseVals":{"enabled":1,"sides":3,"thickoutline":1,"num_inst":100,"x":0.39,"rad":0.59951,"tex_zoom":0.73458,"g":1,"b":1,"b2":1,"a2":1,"border_a":0},"init_eqs_str":"a.sa=0;","frame_eqs_str":"a.sa=div(a.instance,a.num_inst);a.x=.5-.3*Math.sin(.5*a.time);a.y=.5-.3*Math.sin(.4*a.time);a.rad*=1-a.sa;a.r2=.5+.5*Math.sin(44*a.sa+.4*a.time);a.g2=a.r2;a.ang=a.time+2*Math.sin(.7*a.time)*a.sa;","init_eqs_eel":"","frame_eqs_eel":"sa=instance/num_inst;\n\nx=.5 - .3*sin(.5*time);\ny=.5 - .3*sin(.4*time);\n\nrad=rad*(1-sa);\n\nr2=.5+.5*sin(44*sa+.4*time);\ng2=r2;\n\nang=time+2*sin(.7*time)*sa;"},{"baseVals":{"enabled":1,"sides":40,"thickoutline":1,"num_inst":100,"x":0.45,"y":0.47,"rad":0.59956,"tex_zoom":0.73458,"g":1,"b":1,"b2":1,"a2":1,"border_a":0},"init_eqs_str":"a.sa=0;","frame_eqs_str":"a.sa=div(a.instance,a.num_inst);a.x=.5+.3*Math.sin(.5*a.time);a.y=.5+.3*Math.sin(.4*a.time);a.rad*=1-a.sa;a.r2=.5+.5*Math.sin(44*a.sa+.4*a.time);a.g2=a.r2;a.ang=a.time+2*Math.sin(.7*a.time)*a.sa;","init_eqs_eel":"","frame_eqs_eel":"sa=instance/num_inst;\n\nx=.5 + .3*sin(.5*time);\ny=.5 + .3*sin(.4*time);\n\nrad=rad*(1-sa);\n\nr2=.5+.5*sin(44*sa+.4*time);\ng2=r2;\n\nang=time+2*sin(.7*time)*sa;"}],"waves":[{"baseVals":{"samples":13,"thick":1,"scaling":2.44415,"smoothing":0,"a":0.2,"enabled":0},"init_eqs_str":"","frame_eqs_str":"","point_eqs_str":"x1=.7*q1*sin(sample);\ny1=.5*q1*cos(2*sample);\n\n//// reflections\nx= (int(x1)-x1+x1%2)*pow(-1,1+int(x1));\ny= (int(y1)-y1+y1%2)*pow(-1,1+int(y1));\n\nx=.5+1.67*(x-.5)/q6;\ny=.5+(y-.5)/q6;\n\n\n/// clear random points at borders \na=a*below(abs(x-.5),.4999)*below(abs(y-.5),.4999);\nr=x;        g=y;\n","init_eqs_eel":"","frame_eqs_eel":"","point_eqs_eel":"x1=.7*q1*sin(sample);\ny1=.5*q1*cos(2*sample);\n\n//// reflections\nx= (int(x1)-x1+x1%2)*pow(-1,1+int(x1));\ny= (int(y1)-y1+y1%2)*pow(-1,1+int(y1));\n\nx=.5+1.67*(x-.5)/q6;\ny=.5+(y-.5)/q6;\n\n\n/// clear random points at borders \na=a*below(abs(x-.5),.4999)*below(abs(y-.5),.4999);\nr=x;        g=y;\n"},{"baseVals":{"scaling":7.7518,"smoothing":0,"enabled":0},"init_eqs_str":"","frame_eqs_str":"","point_eqs_str":"","init_eqs_eel":"","frame_eqs_eel":"","point_eqs_eel":""},{"baseVals":{"thick":1,"additive":1,"scaling":5.92556,"smoothing":0,"r":0,"b":0,"enabled":0},"init_eqs_str":"","frame_eqs_str":"","point_eqs_str":"","init_eqs_eel":"","frame_eqs_eel":"","point_eqs_eel":""},{"baseVals":{"thick":1,"additive":1,"scaling":5.92556,"smoothing":0,"g":0,"b":0,"a":0.34,"enabled":0},"init_eqs_str":"","frame_eqs_str":"","point_eqs_str":"","init_eqs_eel":"","frame_eqs_eel":"","point_eqs_eel":""}],"init_eqs_str":"a.q5=0;a.q6=0;a.t=0;a.q1=0;","frame_eqs_str":"a.warp=0;a.zoom=1;a.wave_a=0;a.decay=0;a.q5=a.aspectx;a.q6=a.aspecty;a.t+=div(1,a.fps);a.q1=a.t;","pixel_eqs_str":"","init_eqs_eel":"","frame_eqs_eel":"warp = 0;\nzoom = 1;\nwave_a=0;\ndecay=0;\n\nq5 = aspectx;\nq6 = aspecty;\n\nt=t+1/fps;\nq1=t;","pixel_eqs_eel":"","warp":"","comp":"","warp_hlsl":"","comp_hlsl":""}